bioimageit_formats/__init__.py
bioimageit_formats/_factory.py
bioimageit_formats/_formats.py
bioimageit_formats/_reader.py
bioimageit_formats/_plugins/__init__.py
bioimageit_formats/_plugins/_csv.py
bioimageit_formats/_plugins/_imagetiff.py
bioimageit_formats/_plugins/_imagezarr.py
bioimageit_formats/_plugins/_movietxt.py
bioimageit_formats/_plugins/_pythonscript.py
bioimageit_formats/_plugins/_raw.py
bioimageit_formats/_plugins/_trackmate.py
tests/__init__.py
tests/test_csv.py
bioimageit_formats-0.2.0.dist-info/LICENSE
bioimageit_formats-0.2.0.dist-info/METADATA
bioimageit_formats-0.2.0.dist-info/WHEEL
bioimageit_formats-0.2.0.dist-info/top_level.txt
bioimageit_formats-0.2.0.dist-info/RECORD
