Metadata-Version: 2.1
Name: bioimageit-formats
Version: 0.2.0
Summary: Manage data formats for BioImageIT project
Home-page: https://github.com/bioimageit/bioimageit_formats
Author: Sylvain Prigent and BioImageIT team
Author-email: bioimageit@gmail.com
Classifier: Programming Language :: Python :: 3
Classifier: License :: OSI Approved :: BSD License
Classifier: Operating System :: OS Independent
Requires-Python: >=3.7
License-File: LICENSE
Requires-Dist: numpy
Requires-Dist: pandas
Requires-Dist: scikit-image >=0.18.3
Requires-Dist: zarr >=2.12.0
